scrapy_nimbus/__init__.py
scrapy_nimbus/models.py
scrapy_nimbus/settings.py
scrapy_nimbus/data/__init__.py
scrapy_nimbus/data/db.py
scrapy_nimbus/data/mongodb.py
scrapy_nimbus/data/redis.py
scrapy_nimbus/decorator/__init__.py
scrapy_nimbus/extensions/__init__.py
scrapy_nimbus/extensions/notifications.py
scrapy_nimbus/middlewares/__init__.py
scrapy_nimbus/middlewares/base.py
scrapy_nimbus/middlewares/download.py
scrapy_nimbus/middlewares/phantomjs.py
scrapy_nimbus/middlewares/selenium.py
scrapy_nimbus/pipelines/__init__.py
scrapy_nimbus/pipelines/base.py
scrapy_nimbus/pipelines/file.py
scrapy_nimbus/pipelines/image.py
scrapy_nimbus/pipelines/media.py
scrapy_nimbus/pipelines/qiniu.py
scrapy_nimbus/spiders/__init__.py
scrapy_nimbus/spiders/base.py
scrapy_nimbus/spiders/crawl.py
scrapy_nimbus/spiders/csvfeed.py
scrapy_nimbus/spiders/mixin.py
scrapy_nimbus/spiders/phantomjs.py
scrapy_nimbus/spiders/selenium.py
scrapy_nimbus/spiders/sitemap.py
scrapy_nimbus/spiders/xmlfeed.py
scrapy_nimbus-0.5.3.dist-info/DESCRIPTION.rst
scrapy_nimbus-0.5.3.dist-info/METADATA
scrapy_nimbus-0.5.3.dist-info/RECORD
scrapy_nimbus-0.5.3.dist-info/WHEEL
scrapy_nimbus-0.5.3.dist-info/metadata.json
scrapy_nimbus-0.5.3.dist-info/top_level.txt
